README.md
setup.cfg
setup.py
aws_net_scan/__init__.py
aws_net_scan/__main__.py
aws_net_scan/analyzer.py
aws_net_scan/aws_services_data.py
aws_net_scan/entities.py
aws_net_scan/logger.py
aws_net_scan/printer.py
aws_net_scan/services.py
aws_net_scan/utils.py
aws_net_scan.egg-info/PKG-INFO
aws_net_scan.egg-info/SOURCES.txt
aws_net_scan.egg-info/dependency_links.txt
aws_net_scan.egg-info/entry_points.txt
aws_net_scan.egg-info/requires.txt
aws_net_scan.egg-info/top_level.txt