Metadata-Version: 2.1
Name: aws-net-scan
Version: 0.5.0
Summary: Get useful AWS data regarding VPC networking in a structured output.
Home-page: https://github.com/PauSabatesC/aws-net-scan
Author: github.com/PauSabatesC
License: Apache 2.0
Keywords: aws,network,scan,aws-net-scan,cloud,vpc,ec2
Platform: UNKNOWN
Classifier: Intended Audience :: Developers
Classifier: Natural Language :: English
Classifier: License :: OSI Approved :: Apache Software License
Classifier: Programming Language :: Python
Classifier: Programming Language :: Python :: 3.6
Classifier: Programming Language :: Python :: 3.7
Classifier: Programming Language :: Python :: 3.8
Classifier: Programming Language :: Python :: Implementation :: CPython
Classifier: Programming Language :: Python :: Implementation :: PyPy
Requires-Python: >=3.6, <4
Provides-Extra: deploy
